__init__.py
generalist/BaseGeneralizer.py
generalist/DataFly.py
generalist/DateTimeGeneralizer.py
generalist/NoneGeneralizer.py
generalist/NumericGeneralizer.py
generalist/StringMaskingGeneralizer.py
generalist/__init__.py
generalist-0.1.0.dist-info/LICENSE
generalist-0.1.0.dist-info/METADATA
generalist-0.1.0.dist-info/WHEEL
generalist-0.1.0.dist-info/top_level.txt
generalist-0.1.0.dist-info/RECORD
