Metadata-Version: 2.1
Name: generalist
Version: 0.1.0
Summary: Generalize content for k-anonymity
Author-email: Jacob Reimers <pypi@reimers.io>
License: MIT License
Project-URL: Homepage, https://github.com/jjrdk/generalist
Keywords: k-anonymity,generalize,gdpr,pseudonymization
Classifier: License :: OSI Approved :: MIT License
Classifier: Programming Language :: Python
Classifier: Programming Language :: Python :: 3
Requires-Python: >=3.8
License-File: LICENSE
Requires-Dist: typing >3.0.0
Requires-Dist: tomli ; python_version >= "3.8"
Provides-Extra: dev
Requires-Dist: pip-tools ; extra == 'dev'
Requires-Dist: pytest ; extra == 'dev'
